setup.py
gauss_bino_distributions/Binomialdistribution.py
gauss_bino_distributions/Gaussiandistribution.py
gauss_bino_distributions/Generaldistribution.py
gauss_bino_distributions/__init__.py
gauss_bino_distributions.egg-info/PKG-INFO
gauss_bino_distributions.egg-info/SOURCES.txt
gauss_bino_distributions.egg-info/dependency_links.txt
gauss_bino_distributions.egg-info/not-zip-safe
gauss_bino_distributions.egg-info/top_level.txt