Metadata-Version: 1.0
Name: gauss-bino-distributions
Version: 1.0
Summary: Gaussian and Binomial distributions
Home-page: UNKNOWN
Author: Prasenjit Das
Author-email: UNKNOWN
License: UNKNOWN
Platform: UNKNOWN
